{
  "$schema": "../gen/schemas/desktop-schema.json",
  "identifier": "default",
  "description": "Least-privilege capability for the SonIQ desktop window.",
  "windows": [
    "main"
  ],
  "permissions": [
    "core:default",
    "core:window:allow-start-dragging",
    "dialog:allow-open",
    "dialog:allow-save",
    "store:default",
    "clipboard-manager:allow-write-text",
    {
      "identifier": "opener:allow-open-url",
      "allow": [
        {
          "url": "https://accounts.spotify.com/*"
        },
        {
          "url": "https://open.spotify.com/*"
        },
        {
          "url": "https://www.spotify.com/*"
        },
        {
          "url": "https://www.youtube.com/*"
        }
      ]
    },
    "deep-link:default"
  ]
}